hrcomparison/__about__.py
hrcomparison/__init__.py
hrcomparison/activity_parser.py
hrcomparison/base.py
hrcomparison/chart.py
hrcomparison/fit.py
hrcomparison/gpx.py
hrcomparison/tcx.py
hrcomparison-0.1.0.dist-info/METADATA
hrcomparison-0.1.0.dist-info/WHEEL
hrcomparison-0.1.0.dist-info/entry_points.txt
hrcomparison-0.1.0.dist-info/licenses/LICENSE.txt
hrcomparison-0.1.0.dist-info/RECORD
