Metadata-Version: 2.4
Name: hrcomparison
Version: 0.1.0
Summary: Tool for comparing heart rate data from multiple devices
Project-URL: Homepage, https://andgineer.github.io/hrcomparison/
Project-URL: Documentation, https://andgineer.github.io/hrcomparison/
Author-email: Andrey Sorokin <andrey@sorokin.engineer>
License: Copyright (c) 2025 Andrey Sorokin <andrey@sorokin.engineer>
License-File: LICENSE.txt
Keywords: comparison,fit,garmin,gpx,heart-rate,hr,polar,suunto,tcx
Classifier: License :: OSI Approved :: MIT License
Classifier: Operating System :: OS Independent
Classifier: Programming Language :: Python :: 3
Requires-Python: >=3.11
Requires-Dist: click
Requires-Dist: fitparse
Requires-Dist: gpxpy
Requires-Dist: lxml
Requires-Dist: matplotlib
Requires-Dist: pillow>=10.3.0
